LICENSE
MANIFEST.in
setup.py
django_stardate.egg-info/PKG-INFO
django_stardate.egg-info/SOURCES.txt
django_stardate.egg-info/dependency_links.txt
django_stardate.egg-info/not-zip-safe
django_stardate.egg-info/requires.txt
django_stardate.egg-info/top_level.txt
stardate/__init__.py
stardate/admin.py
stardate/feeds.py
stardate/forms.py
stardate/models.py
stardate/parsers.py
stardate/utils.py
stardate/views.py
stardate/backends/__init__.py
stardate/backends/dropbox.py
stardate/backends/google_drive.py
stardate/backends/local_file.py
stardate/management/__init__.py
stardate/management/commands/__init__.py
stardate/management/commands/import_posts.py
stardate/management/commands/update_social_auth.py
stardate/migrations/0001_initial.py
stardate/migrations/0002_auto_20151031_1551.py
stardate/migrations/0003_auto_20151031_1615.py
stardate/migrations/0004_auto_20160109_1321.py
stardate/migrations/0005_auto_20160109_1343.py
stardate/migrations/0006_auto_20160311_0237.py
stardate/migrations/__init__.py
stardate/templates/stardate/base_blog.html
stardate/templates/stardate/base_stardate.html
stardate/templates/stardate/blog_list.html
stardate/templates/stardate/post_archive.html
stardate/templates/stardate/post_archive_day.html
stardate/templates/stardate/post_archive_month.html
stardate/templates/stardate/post_archive_year.html
stardate/templates/stardate/post_detail.html
stardate/templates/stardate/post_form.html
stardate/templates/stardate/includes/author_list.html
stardate/templates/stardate/includes/breadcrumbs.html
stardate/urls/__init__.py
stardate/urls/blog_urls.py
stardate/urls/index_urls.py