Metadata-Version: 1.1
Name: django-stardate
Version: 0.1.0.a5
Summary: Another django blog app.
Home-page: https://github.com/blturner/django-stardate
Author: Benjamin Turner
Author-email: benturn@gmail.com
License: BSD
Download-URL: https://github.com/blturner/django-stardate/archive/v0.1.0.a5.tar.gz
Platform: UNKNOWN
